polars_pairing-0.1.0.dist-info/METADATA
polars_pairing-0.1.0.dist-info/WHEEL
polars_pairing-0.1.0.dist-info/license_files/LICENSE
polars_pairing/__init__.py
polars_pairing/_internal.pyi
polars_pairing/utils.py
polars_pairing/_internal.abi3.so
polars_pairing-0.1.0.dist-info/RECORD
