Metadata-Version: 2.3
Name: polars-pairing
Version: 0.1.0
Classifier: Programming Language :: Rust
Classifier: Programming Language :: Python :: Implementation :: CPython
Classifier: Programming Language :: Python :: Implementation :: PyPy
License-File: LICENSE
Summary: Polars plugin with pairing functions for nonnegative integers
Author-email: Antonio Camargo <antoniop.camargo@gmail.com>
Requires-Python: >=3.8
Project-URL: homepage, https://github.com/apcamargo/polars-pairing
Project-URL: source, https://github.com/apcamargo/polars-pairing
